{"data":{"_id":3000,"properties":{"id":{"name":"id","kind":"scalar","primary":true,"autoincrement":false,"type":"number","array":false,"runtimeType":"number"},"name":{"name":"name","kind":"scalar","getter":false,"setter":false,"type":"string","array":false,"runtimeType":"string"},"date":{"name":"date","kind":"scalar","getter":false,"setter":false,"type":"Date","array":false,"runtimeType":"Date"},"announceId":{"name":"announceId","kind":"scalar","getter":false,"setter":false,"type":"number","array":false,"runtimeType":"number"},"registrationOpen":{"name":"registrationOpen","kind":"scalar","default":true,"getter":false,"setter":false,"type":"boolean","array":false,"runtimeType":"boolean"},"firstReminderSent":{"name":"firstReminderSent","kind":"scalar","default":false,"getter":false,"setter":false,"type":"boolean","array":false,"runtimeType":"boolean"},"secondReminderSent":{"name":"secondReminderSent","kind":"scalar","default":false,"getter":false,"setter":false,"type":"boolean","array":false,"runtimeType":"boolean"}},"primaryKeys":["id"],"filters":{},"hooks":{},"indexes":[],"uniques":[],"className":"Event","path":"./src/backend/entities/event.ts","name":"Event","abstract":false,"internal":true,"constructorParams":[],"toJsonParams":[],"useCache":true,"compositePK":false,"simplePK":true,"collection":"event"},"origin":"./src/backend/entities/event.ts","hash":"f22f33d4bf7c256c6e42cfa25ca69c1b","version":"6.2.7"}
